{
    "Used Resources": [
        {
            "ip_instance": "zed_madd_1_0",
            "resources": [
                {
                    "LUT": "246"
                },
                {
                    "LUTAsLogic": "246"
                },
                {
                    "LUTMem": "0"
                },
                {
                    "REG": "320"
                },
                {
                    "F7MUX": "0"
                },
                {
                    "F8MUX": "0"
                },
                {
                    "BRAM": "0"
                },
                {
                    "DSP": "2"
                },
                {
                    "GLOBAL_CLOCK_BUFFERS": "0"
                },
                {
                    "MMCM": "0"
                },
                {
                    "PLL": "0"
                }
            ]
        },
        {
            "ip_instance": "zed_mmult_1_0",
            "resources": [
                {
                    "LUT": "372"
                },
                {
                    "LUTAsLogic": "370"
                },
                {
                    "LUTMem": "2"
                },
                {
                    "REG": "464"
                },
                {
                    "F7MUX": "0"
                },
                {
                    "F8MUX": "0"
                },
                {
                    "BRAM": "2"
                },
                {
                    "DSP": "5"
                },
                {
                    "GLOBAL_CLOCK_BUFFERS": "0"
                },
                {
                    "MMCM": "0"
                },
                {
                    "PLL": "0"
                }
            ]
        }
    ]
}
